sihodictapi/__init__.py
sihodictapi/utils.py
sihodictapi/dictionaries/__init__.py
sihodictapi/dictionaries/baidu.py
sihodictapi/dictionaries/cnki.py
sihodictapi/dictionaries/foxit.py
sihodictapi/dictionaries/google.py
sihodictapi/dictionaries/hujiang.py
sihodictapi/dictionaries/iciba.py
sihodictapi/dictionaries/moji.py
sihodictapi/dictionaries/souka.py
sihodictapi/dictionaries/youdao.py
sihodictapi-0.1.26.dist-info/LICENSE
sihodictapi-0.1.26.dist-info/METADATA
sihodictapi-0.1.26.dist-info/WHEEL
sihodictapi-0.1.26.dist-info/top_level.txt
sihodictapi-0.1.26.dist-info/RECORD
