Metadata-Version: 2.1
Name: sihodictapi
Version: 0.1.26
Summary: 一些在线词典/翻译API
License: MIT
Classifier: License :: OSI Approved :: MIT License
License-File: LICENSE
Requires-Dist: requestspr (>=0.0.3)
Requires-Dist: beautifulsoup4
Requires-Dist: pycryptodome
